retrying.py
retrying_hk-1.4.1.dist-info/licenses/AUTHORS.rst
retrying_hk-1.4.1.dist-info/licenses/LICENSE
retrying_hk-1.4.1.dist-info/licenses/NOTICE
retrying_hk-1.4.1.dist-info/METADATA
retrying_hk-1.4.1.dist-info/WHEEL
retrying_hk-1.4.1.dist-info/top_level.txt
retrying_hk-1.4.1.dist-info/RECORD
