Metadata-Version: 2.4
Name: retrying-hk
Version: 1.4.1
Summary: Python retrying library, forked from groodt/retrying
Home-page: https://github.com/groodt/retrying
Author: Greg Roodt
Author-email: Hugo Klepsch <hugo.klepsch@gmail.com>
License: Apache 2.0
Keywords: decorator decorators retry retrying exception exponential backoff
Classifier: Intended Audience :: Developers
Classifier: Natural Language :: English
Classifier: License :: OSI Approved :: Apache Software License
Classifier: Programming Language :: Python
Classifier: Programming Language :: Python :: 3
Classifier: Programming Language :: Python :: 3 :: Only
Classifier: Programming Language :: Python :: 3.7
Classifier: Programming Language :: Python :: 3.8
Classifier: Programming Language :: Python :: 3.9
Classifier: Programming Language :: Python :: 3.10
Classifier: Programming Language :: Python :: 3.11
Classifier: Programming Language :: Python :: 3.12
Classifier: Programming Language :: Python :: 3.13
Classifier: Programming Language :: Python :: Implementation :: CPython
Classifier: Topic :: Internet
Classifier: Topic :: Utilities
Requires-Python: >=3.6
License-File: LICENSE
License-File: NOTICE
License-File: AUTHORS.rst
Dynamic: author
Dynamic: classifier
Dynamic: description
Dynamic: home-page
Dynamic: keywords
Dynamic: license
Dynamic: license-file
Dynamic: requires-python
